odoo/addons/edi_account_oca/README.rst
odoo/addons/edi_account_oca/__init__.py
odoo/addons/edi_account_oca/__manifest__.py
odoo/addons/edi_account_oca/i18n/edi_account.pot
odoo/addons/edi_account_oca/i18n/edi_account_oca.pot
odoo/addons/edi_account_oca/i18n/fr.po
odoo/addons/edi_account_oca/i18n/it.po
odoo/addons/edi_account_oca/migrations/18.0.1.1.0/pre-migration.py
odoo/addons/edi_account_oca/models/__init__.py
odoo/addons/edi_account_oca/models/account_move.py
odoo/addons/edi_account_oca/readme/CONTRIBUTORS.md
odoo/addons/edi_account_oca/readme/DESCRIPTION.md
odoo/addons/edi_account_oca/static/description/icon.png
odoo/addons/edi_account_oca/static/description/index.html
odoo/addons/edi_account_oca/tests/__init__.py
odoo/addons/edi_account_oca/tests/test_edi.py
odoo_addon_edi_account_oca-18.0.1.1.1.1.dist-info/METADATA
odoo_addon_edi_account_oca-18.0.1.1.1.1.dist-info/WHEEL
odoo_addon_edi_account_oca-18.0.1.1.1.1.dist-info/top_level.txt
odoo_addon_edi_account_oca-18.0.1.1.1.1.dist-info/RECORD
